myHealth/__init__.py
myHealth/medication.py
myHealth/myHealth.py
myHealth/myMedication.csv
myHealth/myVitals.csv
myHealth/utility.py
myHealth/visualisation.py
myHealth/vitals.py
myhealth-1.0.dist-info/METADATA
myhealth-1.0.dist-info/WHEEL
myhealth-1.0.dist-info/licenses/LICENSE
myhealth-1.0.dist-info/RECORD
