Metadata-Version: 2.3
Name: myHealth
Version: 1.0
Summary: A Python app that helps patients generate simple personal medical history reports for doctor's appointments.
Project-URL: Documentation, https://myhealth.readthedocs.io/en/latest/
Project-URL: Repository, https://github.com/sy8low/myHealth
Project-URL: PyPI, https://pypi.org/project/myHealth/
Project-URL: Youtube, https://www.youtube.com/watch?v=v23E7wb9Ykc
Author: Sze Yoong Low
Maintainer: Sze Yoong Low
License:                     GNU AFFERO GENERAL PUBLIC LICENSE
License-File: LICENSE
Keywords: algorithm,command line,cs50,data,data analytics,data science,healthcare,matplotlib,numpy,object-oriented prgramming,pandas,pytest,recursion,statistics,unit test
Classifier: Development Status :: 5 - Production/Stable
Classifier: Intended Audience :: Healthcare Industry
Classifier: License :: OSI Approved :: GNU Affero General Public License v3
Classifier: Natural Language :: English
Classifier: Operating System :: OS Independent
Classifier: Programming Language :: Python :: 3.10
Classifier: Topic :: Database
Requires-Python: >=3.0
Requires-Dist: matplotlib>=3.9.0
Requires-Dist: numpy>=1.26.4
Requires-Dist: pandas>=2.2.2
Requires-Dist: pytest>=8.2.1
Requires-Dist: tabulate>=0.9.0
